{
  "variants": {
    "distance=0": {
      "model": "zirconmod:block/mist"
    },
    "distance=1": {
      "model": "zirconmod:block/mist"
    },
    "distance=10": {
      "model": "zirconmod:block/mist"
    },
    "distance=11": {
      "model": "zirconmod:block/mist"
    },
    "distance=12": {
      "model": "zirconmod:block/mist"
    },
    "distance=13": {
      "model": "zirconmod:block/mist"
    },
    "distance=14": {
      "model": "zirconmod:block/mist"
    },
    "distance=15": {
      "model": "zirconmod:block/mist_passable"
    },
    "distance=2": {
      "model": "zirconmod:block/mist"
    },
    "distance=3": {
      "model": "zirconmod:block/mist"
    },
    "distance=4": {
      "model": "zirconmod:block/mist"
    },
    "distance=5": {
      "model": "zirconmod:block/mist"
    },
    "distance=6": {
      "model": "zirconmod:block/mist"
    },
    "distance=7": {
      "model": "zirconmod:block/mist"
    },
    "distance=8": {
      "model": "zirconmod:block/mist"
    },
    "distance=9": {
      "model": "zirconmod:block/mist"
    }
  }
}